{
  "users": [
    {
      "id": 1,
      "name": "John Doe",
      "email": "teste@teste.com",
      "department": "IT"
    },
    {
      "id": 2,
      "name": "Jane Doe",
      "email": "teste@teste.com",
      "department": "IA"
    }
  ],
  "tasks": [
    {
      "title": "AppTasks",
      "description": "criar CRUDs",
      "id": 1
    },
    {
      "title": "AppTasks",
      "description": "cria integração",
      "id": 2
    },
    {
      "title": "AppTask",
      "description": "CRUD Back End",
      "id": 3
    },
    {
      "title": "Cintia",
      "description": "coral IPI",
      "id": 4
    }
  ]
}